fcm_client-0.2.2.dist-info/METADATA
fcm_client-0.2.2.dist-info/RECORD
fcm_client-0.2.2.dist-info/WHEEL
fcm_client-0.2.2.dist-info/entry_points.txt
fcm_client-0.2.2.dist-info/top_level.txt
fcmclient/VERSION
fcmclient/__init__.py
fcmclient/api.py
fcmclient/cli.py
fcmclient/version.py
