Metadata-Version: 2.1
Name: fcm-client
Version: 0.2.2
Summary: Python client for Firebase Cloud Messaging (FCM)
Home-page: https://github.com/happybits/fcm-client
Author: John Loehrer
Author-email: 72squared@gmail.com
License: Apache 2.0
Keywords: fcm push notification google cloud messaging android
Platform: UNKNOWN
Classifier: Development Status :: 4 - Beta
Classifier: Intended Audience :: Developers
Classifier: License :: OSI Approved :: Apache Software License
Classifier: Programming Language :: Python
Classifier: Topic :: Software Development :: Libraries :: Python Modules
Requires-Dist: requests
Requires-Dist: six
